[
  {
    "Id": "build1",
    "Name": "大型の貨物船室",
    "Group": "貨物船内装モジュール",
    "Description": "この拡張モジュールを使用すると、\n大型の宇宙船内部に居住空間を\n素早く建設できる。\n \n建設用ユニットはあらかじめ\n組み立ててあり、圧力隔壁と必要な\n接続用ポイントも付属している。"
  },
  {
    "Id": "build2",
    "Name": "貨物船用通路",
    "Group": "貨物船内装モジュール",
    "Description": "この拡張モジュールを使用すると、\n大型の宇宙船内部に居住空間を\n素早く建設できる。\n \n建設用ユニットはあらかじめ\n組み立ててあり、圧力隔壁と必要な\n接続用ポイントも付属している。"
  },
  {
    "Id": "build3",
    "Name": "カーブした貨物船用通路",
    "Group": "貨物船内装モジュール",
    "Description": "この拡張モジュールを使用すると、\n大型の宇宙船内部に居住空間を\n素早く建設できる。\n \n建設用ユニットはあらかじめ\n組み立ててあり、圧力隔壁と必要な\n接続用ポイントも付属している。"
  },
  {
    "Id": "build4",
    "Name": "貨物船用接合部",
    "Group": "貨物船内装モジュール",
    "Description": "この拡張モジュールを使用すると、\n大型の宇宙船内部に居住空間を\n素早く建設できる。\n \n建設用ユニットはあらかじめ\n組み立ててあり、圧力隔壁と必要な\n接続用ポイントも付属している。"
  },
  {
    "Id": "build5",
    "Name": "貨物船用階段",
    "Group": "貨物船内装モジュール",
    "Description": "この拡張モジュールを使用すると、\n大型の宇宙船内部に居住空間を\n素早く建設できる。\n \n建設用ユニットはあらかじめ\n組み立ててあり、圧力隔壁と必要な\n接続用ポイントも付属している。"
  },
  {
    "Id": "build6",
    "Name": "貨物船用交差路",
    "Group": "貨物船内装モジュール",
    "Description": "この拡張モジュールを使用すると、\n大型の宇宙船内部に居住空間を\n素早く建設できる。\n \n建設用ユニットはあらかじめ\n組み立ててあり、圧力隔壁と必要な\n接続用ポイントも付属している。"
  },
  {
    "Id": "build8",
    "Name": "木製の壁",
    "Group": "木製の建造部品",
    "Description": "基地建設に使用する木製の壁。"
  },
  {
    "Id": "build9",
    "Name": "薄い木製の壁",
    "Group": "木製の建造部品",
    "Description": "基地建設に使用する薄い木製の壁"
  },
  {
    "Id": "build10",
    "Name": "小さな木製の壁",
    "Group": "木製の建造部品",
    "Description": "基地建設に使用する小さな木製の壁。"
  },
  {
    "Id": "build11",
    "Name": "低い木製の壁",
    "Group": "木製の建造部品",
    "Description": "基地建設に使用する低い木製の壁"
  },
  {
    "Id": "build12",
    "Name": "木製のスロープパネル",
    "Group": "木製の建造部品",
    "Description": "基地建設に使用する木製のスロープパネル。"
  },
  {
    "Id": "build13",
    "Name": "木製の窓パネル",
    "Group": "木製の建造部品",
    "Description": "基地建設に使用する木製の窓パネル。"
  },
  {
    "Id": "build14",
    "Name": "木製のドア枠",
    "Group": "木製の建造部品",
    "Description": "基地建設に使用する木製のドア枠。"
  },
  {
    "Id": "build15",
    "Name": "木製の戸口",
    "Group": "木製の建造部品",
    "Description": "基地建設に使用する木製の戸口"
  },
  {
    "Id": "build16",
    "Name": "木製の間口",
    "Group": "木製の建造部品",
    "Description": "基地建設に使用する木製の間口。"
  },
  {
    "Id": "build17",
    "Name": "木製のフロアパネル",
    "Group": "木製の建造部品",
    "Description": "基地建設に使用する木製のフロアパネル。"
  },
  {
    "Id": "build18",
    "Name": "木製フレームのガラスパネル",
    "Group": "木製の建造部品",
    "Description": "木製フレームのガラスの床/天井パネル。"
  },
  {
    "Id": "build19",
    "Name": "小さな木製のパネル",
    "Group": "木製の建造部品",
    "Description": "基地建設に使用する小さな木製のパネル。"
  },
  {
    "Id": "build20",
    "Name": "木製の傾斜台",
    "Group": "木製の建造部品",
    "Description": "基地建設に使用する木製の傾斜台。"
  },
  {
    "Id": "build21",
    "Name": "木製の半傾斜台",
    "Group": "木製の建造部品",
    "Description": "基地建設に使用する木製の半傾斜台。"
  },
  {
    "Id": "build22",
    "Name": "木製の天井",
    "Group": "木製の建造部品",
    "Description": "強化済み支柱付きの標準的な天井。"
  },
  {
    "Id": "build23",
    "Name": "木製の屋根パネル",
    "Group": "木製の建造部品",
    "Description": "基地建設に使用する木製の屋根パネル"
  },
  {
    "Id": "build24",
    "Name": "木製の角屋根",
    "Group": "木製の建造部品",
    "Description": "基地建設に使用する木製の角屋根"
  },
  {
    "Id": "build25",
    "Name": "木製のアーチ",
    "Group": "木製の建造部品",
    "Description": "基地建設に使用する木製のアーチ。"
  },
  {
    "Id": "build26",
    "Name": "木製の半アーチ",
    "Group": "木製の建造部品",
    "Description": "基地建設に使用する木製の半アーチ。"
  },
  {
    "Id": "build27",
    "Name": "コンクリート製の壁",
    "Group": "コンクリート製の建造部品",
    "Description": "基地建設に使用するコンクリート製の壁。"
  },
  {
    "Id": "build28",
    "Name": "薄いコンクリート製の壁",
    "Group": "コンクリート製の建造部品",
    "Description": "基地建設に使用する薄いコンクリート製の壁"
  },
  {
    "Id": "build29",
    "Name": "小さなコンクリート製の壁",
    "Group": "コンクリート製の建造部品",
    "Description": "基地建設に使用する小さなコンクリート製の壁。"
  },
  {
    "Id": "build30",
    "Name": "低いコンクリート製の壁",
    "Group": "コンクリート製の建造部品",
    "Description": "基地建設に使用する低いコンクリート製の壁"
  },
  {
    "Id": "build31",
    "Name": "コンクリート製のスロープパネル",
    "Group": "コンクリート製の建造部品",
    "Description": "基地建設に使用するコンクリート製のスロープパネル。"
  },
  {
    "Id": "build32",
    "Name": "コンクリート製のウィンドウパネル",
    "Group": "コンクリート製の建造部品",
    "Description": "基地建設に使用するコンクリート製のウィンドウパネル。"
  },
  {
    "Id": "build33",
    "Name": "コンクリート製のドアフレーム",
    "Group": "コンクリート製の建造部品",
    "Description": "基地建設に使用するコンクリート製のドアフレーム。"
  },
  {
    "Id": "build34",
    "Name": "コンクリート製の戸口",
    "Group": "コンクリート製の建造部品",
    "Description": "基地建設に使用するコンクリート製の戸口"
  },
  {
    "Id": "build35",
    "Name": "コンクリート製の玄関",
    "Group": "コンクリート製の建造部品",
    "Description": "基地建設に使用するコンクリート製の玄関。"
  },
  {
    "Id": "build36",
    "Name": "コンクリート製のフロアパネル",
    "Group": "コンクリート製の建造部品",
    "Description": "基地建設に使用するコンクリート製のフロアパネル。"
  },
  {
    "Id": "build37",
    "Name": "コンクリートフレームのガラスパネル",
    "Group": "コンクリート製の建造部品",
    "Description": "コンクリートフレームのガラスの床/天井パネル。"
  },
  {
    "Id": "build38",
    "Name": "小さなコンクリート製のパネル",
    "Group": "コンクリート製の建造部品",
    "Description": "基地建設に使用する小さなコンクリート製のパネル。"
  },
  {
    "Id": "build39",
    "Name": "コンクリート製の傾斜台",
    "Group": "コンクリート製の建造部品",
    "Description": "基地建設に使用するコンクリート製の傾斜台。"
  },
  {
    "Id": "build40",
    "Name": "コンクリート製の半傾斜台",
    "Group": "コンクリート製の建造部品",
    "Description": "基地建設に使用するコンクリート製の半傾斜台。"
  },
  {
    "Id": "build41",
    "Name": "コンクリート製の屋根",
    "Group": "コンクリート製の建造部品",
    "Description": "強化済み支柱付きの標準的な天井。"
  },
  {
    "Id": "build42",
    "Name": "コンクリート製の屋根パネル",
    "Group": "コンクリート製の建造部品",
    "Description": "基地建設に使用するコンクリート製の屋根パネル"
  },
  {
    "Id": "build43",
    "Name": "コンクリート製の角屋根",
    "Group": "コンクリート製の建造部品",
    "Description": "基地建設に使用するコンクリート製の角屋根"
  },
  {
    "Id": "build44",
    "Name": "コンクリート製のアーチ",
    "Group": "コンクリート製の建造部品",
    "Description": "基地建設に使用するコンクリート製のアーチ。"
  },
  {
    "Id": "build45",
    "Name": "コンクリート製の半アーチ",
    "Group": "コンクリート製の建造部品",
    "Description": "基地建設に使用するコンクリート製の半アーチ。"
  },
  {
    "Id": "build46",
    "Name": "金属製の壁",
    "Group": "金属製の建造部品",
    "Description": "基地建設に使用する金属製の壁。"
  },
  {
    "Id": "build47",
    "Name": "薄い金属製の壁",
    "Group": "金属製の建造部品",
    "Description": "基地建設に使用する薄い金属製の壁"
  },
  {
    "Id": "build48",
    "Name": "小さな金属製の壁",
    "Group": "金属製の建造部品",
    "Description": "基地建設に使用する小さな金属製の壁。"
  },
  {
    "Id": "build49",
    "Name": "低い金属製の壁",
    "Group": "金属製の建造部品",
    "Description": "基地建設に使用する小さな金属製の壁"
  },
  {
    "Id": "build50",
    "Name": "金属製のスロープパネル",
    "Group": "金属製の建造部品",
    "Description": "基地建設に使用する金属製のスロープパネル。"
  },
  {
    "Id": "build51",
    "Name": "金属製のウィンドウパネル",
    "Group": "金属製の建造部品",
    "Description": "基地建設に使用する金属製のウィンドウパネル。"
  },
  {
    "Id": "build52",
    "Name": "金属性のドアフレーム",
    "Group": "金属製の建造部品",
    "Description": "基地建設に使用する金属製のドアフレーム。"
  },
  {
    "Id": "build53",
    "Name": "金属製の戸口",
    "Group": "金属製の建造部品",
    "Description": "基地建設に使用する金属製の戸口"
  },
  {
    "Id": "build54",
    "Name": "金属製の玄関",
    "Group": "金属製の建造部品",
    "Description": "基地建設に使用する金属製の玄関。"
  },
  {
    "Id": "build55",
    "Name": "金属製のフロアパネル",
    "Group": "金属製の建造部品",
    "Description": "基地建設に使用する金属製のフロアパネル。"
  },
  {
    "Id": "build56",
    "Name": "金属フレームのガラスパネル",
    "Group": "金属製の建造部品",
    "Description": "金属フレームのガラスの床/天井パネル。"
  },
  {
    "Id": "build57",
    "Name": "小さな金属製のパネル",
    "Group": "金属製の建造部品",
    "Description": "基地建設に使用する小さな金属製のパネル。"
  },
  {
    "Id": "build58",
    "Name": "金属製の傾斜台",
    "Group": "金属製の建造部品",
    "Description": "基地建設に使用する金属製の傾斜台。"
  },
  {
    "Id": "build59",
    "Name": "金属製の半傾斜台",
    "Group": "金属製の建造部品",
    "Description": "基地建設に使用する金属製の半傾斜台。"
  },
  {
    "Id": "build60",
    "Name": "金属製の屋根",
    "Group": "金属製の建造部品",
    "Description": "強化済み支柱付きの標準的な天井。"
  },
  {
    "Id": "build61",
    "Name": "金属製の屋根パネル",
    "Group": "金属製の建造部品",
    "Description": "基地建設に使用する金属製の屋根パネル"
  },
  {
    "Id": "build62",
    "Name": "金属製の角屋根",
    "Group": "金属製の建造部品",
    "Description": "基地建設に使用する金属製の角屋根"
  },
  {
    "Id": "build63",
    "Name": "金属製のアーチ",
    "Group": "金属製の建造部品",
    "Description": "基地建設に使用する金属製のアーチ。"
  },
  {
    "Id": "build64",
    "Name": "金属製の半アーチ",
    "Group": "金属製の建造部品",
    "Description": "基地建設に使用する金属製の半アーチ。"
  },
  {
    "Id": "build65",
    "Name": "円柱状の部屋",
    "Group": "建設モジュール",
    "Description": "基礎建築のコアモジュール。拡張可能の中心スペースができる。"
  },
  {
    "Id": "build66",
    "Name": "四角い部屋",
    "Group": "建設モジュール",
    "Description": "基礎建築のコアモジュールの四角い版。広い中心スペースは拡張可能。"
  },
  {
    "Id": "build67",
    "Name": "直進通路",
    "Group": "建設モジュール",
    "Description": "部屋の連結に使用する標準的な直線の通路モジュール。"
  },
  {
    "Id": "build68",
    "Name": "L字型通路",
    "Group": "建設モジュール",
    "Description": "部屋の連結に使用するL字型に曲がった頑丈な通路モジュール。"
  },
  {
    "Id": "build69",
    "Name": "T字型通路",
    "Group": "AAST",
    "Description": "部屋の連結に使用する分岐したT字型の通路モジュール。"
  },
  {
    "Id": "build70",
    "Name": "十字型通路",
    "Group": "建設モジュール",
    "Description": "4部屋を十字型に連結する際に使用する十字型の通路モジュール。"
  },
  {
    "Id": "build71",
    "Name": "曲がった通路",
    "Group": "建設モジュール",
    "Description": "部屋の連結に使用する、カーブのついた頑丈な通路モジュール。"
  },
  {
    "Id": "build72",
    "Name": "ガラス天井の廊下",
    "Group": "建築モジュール",
    "Description": "強化ガラス天井の廊下。"
  },
  {
    "Id": "build73",
    "Name": "展望球",
    "Group": "建築モジュール",
    "Description": "自己完結型の球状の展望台。素晴らしい眺望を楽しめる。"
  },
  {
    "Id": "build74",
    "Name": "バイオドーム",
    "Group": "建築モジュール",
    "Description": "さまざまな植物を栽培するのに最適な、ドーム仕様の魅力的な部屋。"
  },
  {
    "Id": "build75",
    "Name": "立方体の部屋",
    "Group": "建築モジュール",
    "Description": "より大型の構造物を作るために積み重ねたり繋げたりできる小型の立方体建築モジュール。"
  },
  {
    "Id": "build76",
    "Name": "大きなキューブ",
    "Group": "デコレーション",
    "Description": "閉ざされた立方体部屋。"
  },
  {
    "Id": "build77",
    "Name": "ガラスの立方体部屋",
    "Group": "建築モジュール",
    "Description": "ほぼガラスのみで出来た立方体部屋モジュール。美しい自然の景観を眺めるのによい。"
  },
  {
    "Id": "build78",
    "Name": "カーブした立方体部屋の壁",
    "Group": "建築モジュール",
    "Description": "立方体部屋用のカーブした壁モジュール。積み上げたりつなげたりすることで大きな構造物を作成できる。"
  },
  {
    "Id": "build79",
    "Name": "カーブした立方体部屋の屋根",
    "Group": "建築モジュール",
    "Description": "全面がガラス張りのカーブした屋根モジュール。積み上げたりつなげたりすることで大きな構造物を作成できる。"
  },
  {
    "Id": "build80",
    "Name": "屋内階段",
    "Group": "建築モジュール",
    "Description": "立方体状の構造物内での移動性を向上させる階段。"
  },
  {
    "Id": "build81",
    "Name": "立方体部屋の室内ドア",
    "Group": "建築モジュール",
    "Description": "立方体部屋を区切るのに使う室内ドアモジュール。"
  },
  {
    "Id": "build82",
    "Name": "立方体部屋の内壁",
    "Group": "建築モジュール",
    "Description": "立方体部屋を区切るのに使う内壁モジュール。"
  },
  {
    "Id": "build83",
    "Name": "立方体部屋のフローリング",
    "Group": "建設アイテム",
    "Description": "立方体部屋用にカットされた耐摩耗用合成フロアパネル。"
  },
  {
    "Id": "build84",
    "Name": "ドア",
    "Group": "建設アイテム",
    "Description": "全ての部屋や通路に使用できる圧縮密閉される標準的なドア。"
  },
  {
    "Id": "build85",
    "Name": "傾斜台",
    "Group": "建設アイテム",
    "Description": "建物へのアクセスを可能にする強化された傾斜台。"
  },
  {
    "Id": "build86",
    "Name": "敷石",
    "Group": "建設アイテム",
    "Description": "耐摩耗性の複合材料の敷石。歩道と舗装されたエリアの建設に使用される。"
  },
  {
    "Id": "build87",
    "Name": "基礎はしご",
    "Group": "建築モジュール",
    "Description": "構造用の床材と組み合わせて使えるはしご。簡単に高所へ行けるようになる。"
  },
  {
    "Id": "build88",
    "Name": "ファウンデーション",
    "Group": "建築モジュール",
    "Description": "すべての建築プロジェクトのベースとなるユニット。どんな構造に対しても強固な基盤を提供する。あらゆる地形に固定できる。"
  },
  {
    "Id": "build89",
    "Name": "円柱状の部屋の骨組み",
    "Group": "建築モジュール",
    "Description": "標準的な円柱部屋に使える軽量の産業用骨組み。"
  },
  {
    "Id": "build90",
    "Name": "立方体部屋の骨組み",
    "Group": "建築モジュール",
    "Description": "立方体部屋用の軽量の骨組み。積み上げたりつなげたりすることで大きな産業構造物を作成できる。"
  },
  {
    "Id": "build91",
    "Name": "敷石",
    "Group": "建設アイテム",
    "Description": "耐摩耗性の複合材料の敷石。歩道と舗装されたエリアの建設に使用される。"
  },
  {
    "Id": "build92",
    "Name": "立方体部屋の基礎支柱4本セット",
    "Group": "建設アイテム",
    "Description": "立方体の部屋を支える作成済みの4本足のセット。"
  },
  {
    "Id": "build93",
    "Name": "立方体部屋の基礎支柱",
    "Group": "建設アイテム",
    "Description": "立方体の部屋を支える安定した柱。"
  },
  {
    "Id": "build94",
    "Name": "窓",
    "Group": "建設アイテム",
    "Description": "自動洗浄機能付きでUV対応済みの密封されたガラスで作られた窓。"
  },
  {
    "Id": "build95",
    "Name": "ガラスパネル大",
    "Group": "建設アイテム",
    "Description": "自動洗浄機能付きでUV対応済みの密封されたガラスで作られた窓。"
  },
  {
    "Id": "build96",
    "Name": "窓",
    "Group": "建設アイテム",
    "Description": "自動洗浄機能付きでUV対応済みの密封されたガラスで作られた窓。"
  },
  {
    "Id": "build97",
    "Name": "窓",
    "Group": "建設アイテム",
    "Description": "自動洗浄機能付きでUV対応済みの密封されたガラスで作られた窓。"
  },
  {
    "Id": "build98",
    "Name": "窓",
    "Group": "建設アイテム",
    "Description": "自動洗浄機能付きでUV対応済みの密封されたガラスで作られた窓。"
  },
  {
    "Id": "build106",
    "Name": "基地復旧カプセル",
    "Group": "自律型保管装置",
    "Description": "建設の復旧装置。\n\nこの追加テクノロジーは、直前の基地の破壊後に残されたものを保管する。"
  },
  {
    "Id": "build118",
    "Name": "大気収集機",
    "Group": "自動ガス圧縮機",
    "Description": "貴重な気体を採取するための自動サイフォン\nユニット。起動すると大気中の物質をゆっくりと\n凝結、圧縮する。圧縮された気体は回収まで安全に\n格納される。"
  },
  {
    "Id": "build129",
    "Name": "ガンマウィード",
    "Group": "栽培可能な種",
    "Description": "放射性の生物群集でよく育つ\n発光する広葉顕花植物。\n頻繁に収穫することができ、収量も多い。\n\n屋内の水栽培に適している。\n屋外に植える場合は放射性の気候であることを確認する。\n\nおおよその成育時間：4時間"
  },
  {
    "Id": "build130",
    "Name": "ファンガルクラスター",
    "Group": "栽培可能な種",
    "Description": "内部にヒダをもつ球形のキノコで\n毒性の生物群集でのみ見つかる。\n移植して培養することができ、早生で収量は多い。\n\n屋内の水栽培に適している。屋外に植える場合は\n毒性の気候であることを確認する。\n\nおおよその成育時間：4時間"
  },
  {
    "Id": "build131",
    "Name": "フロストワート",
    "Group": "栽培可能な種",
    "Description": "青く光り輝く花が咲く大型のクリスタルフラワー。\n雪の多い生物群集でのみ見つかる。\n栽培することができ、安定した収量をもたらす。\n厳しい環境に適応した結果、収穫頻度は高い。\n屋内の水栽培に適している。屋外に植える場合は\n極寒気候であることを確認する。\n\nおおよその成育時間：1時間"
  },
  {
    "Id": "build132",
    "Name": "ベノムアーチン",
    "Group": "栽培可能な種",
    "Description": "効能のある少量の毒液嚢を定期的に分泌する、\n小型で無害そうな見た目の植物。\n価値のある貿易財。\n\n屋内の水栽培に適している。\n屋外に植えることはできない。\n\nおおよその成育時間：3時間20分"
  },
  {
    "Id": "build133",
    "Name": "ソーラーヴァイン",
    "Group": "栽培可能な種",
    "Description": "この「生ける岩」は焦土の生物群集の極度の高温に\n適応して生えている。栽培時はほとんどの環境で\n生育可能で、一旦定着すると中規模の収量を\nもたらすが収穫頻度は低い。\n屋内の水栽培に適している。\n屋外に植える場合は高温気候であることを確認する。\n\nおおよその成育時間：16時間"
  },
  {
    "Id": "build134",
    "Name": "ガットロットフラワー",
    "Group": "栽培可能な種",
    "Description": "嫌な臭いのする栽培可能な花で、糞便物質の\n化学構造を複製する。屋内に植えると、\nフェシウムを頻繁に産出する。\nフェシウムを手で集めるには動物に餌をやり、\nその糞を回収するが、それよりも手間がかからない\nガットロットフラワーは水栽培トレーで育てる\n必要がある。\nおおよその成育時間：4時間"
  },
  {
    "Id": "build135",
    "Name": "グラビティーノホスト",
    "Group": "栽培可能な種",
    "Description": "奇妙で、寄生の可能性がある植物。\n貿易財として評価の高いグラビティーノボールを\n不定期に収穫できる。\n\n屋内の水栽培に適している。\n屋外に植えることはできない。\n\nおおよその成育時間：2時間"
  },
  {
    "Id": "build136",
    "Name": "モーダイトの根",
    "Group": "栽培可能な種",
    "Description": "食用ではない塊茎。ある程度の頻度で少量の\nモーダイトクリスタルを産出する。\n\n生き物の死骸からモーダイトを収穫するよりも\n害のない方法。モーダイトの根は水栽培トレーで\n育てる必要がある。\n\nおおよその成育時間：8時間"
  },
  {
    "Id": "build137",
    "Name": "エキノカクタス",
    "Group": "栽培可能な種",
    "Description": "不毛の生物群集原産で長期間の渇水に耐える\n食用多肉植物。根付きが良く収量は多いが、\n収穫頻度は不定期である。\n\n屋内の水栽培に適している。屋外に植える場合は\n不毛の気候であることを確認する。\n\nおおよその成育時間：16時間"
  },
  {
    "Id": "build138",
    "Name": "スターブランブル",
    "Group": "栽培可能な種",
    "Description": "中型の栽培可能植物。貴重なスターバルブを\n不定期に採集できる。\n\n屋内での水栽培に適している。屋外に植える場合は\n恵まれた気候でなければならない。\n\nおおよその成育時間：4時間"
  },
  {
    "Id": "build139",
    "Name": "アルブミンパール・オーブ",
    "Group": "球状植物",
    "Description": "価値のあるアルブミンパールの\n定期的な収穫をもたらす中型の\n栽培可能な結晶玉。\n\n屋内の水栽培に適している。\n屋外に植えることはできない。\n\nおおよその成育時間：\n80分"
  },
  {
    "Id": "build140",
    "Name": "ニップニップ",
    "Group": "栽培可能な種",
    "Description": "この薬用ハーブは、刺激臭のあるつぼみからゲックニップが生産できることで有名だ。ニップニップは湿った環境で育ち、しばしば雑草に交じって生えている。\n\n屋内の水栽培に適している。屋外に植える場合は熱帯または湿度の高い気候が必要。"
  },
  {
    "Id": "build141",
    "Name": "植物格納容器",
    "Group": "デコレーション",
    "Description": "基地を美しくするための建築用の装飾品。"
  },
  {
    "Id": "build142",
    "Name": "鉢植え植物",
    "Group": "デコレーション",
    "Description": "室内植物用の装飾鉢。"
  },
  {
    "Id": "build145",
    "Name": "スタンドプランター",
    "Group": "農業技術",
    "Description": "農作物を室内で栽培するためのスタンドプランター一式。"
  },
  {
    "Id": "build146",
    "Name": "バレル製造機",
    "Group": "ファブリケーター",
    "Description": "建設者のために便利なアイテムを定期的に作成する。\nアイテムを回収するにはアトラスパス ver1によるID認証が必要。"
  },
  {
    "Id": "build147",
    "Name": "箱製造機",
    "Group": "デコレーション",
    "Description": "基地を美しくするための建築用の装飾品。"
  },
  {
    "Id": "build150",
    "Name": "鍵付き木箱",
    "Group": "ファブリケーター",
    "Description": "建設者のために便利なアイテムを定期的に作成する。"
  },
  {
    "Id": "build151",
    "Name": "小さな木箱",
    "Group": "デコレーション",
    "Description": "基地を美しくするための建築用の装飾品。"
  },
  {
    "Id": "build152",
    "Name": "ウェポンラック",
    "Group": "デコレーション",
    "Description": "基地を美しくするための建築用の装飾品。"
  },
  {
    "Id": "build153",
    "Name": "チェア",
    "Group": "家具",
    "Description": "ほとんどの2足歩行種族に対応するようデザインされた座り心地の良い椅子。お尻にあたる部分が少ししびれる。"
  },
  {
    "Id": "build154",
    "Name": "チェア",
    "Group": "家具",
    "Description": "ほとんどの2足歩行種族に対応するようデザインされた座り心地の良い椅子。お尻にあたる部分が少ししびれる。"
  },
  {
    "Id": "build155",
    "Name": "チェア",
    "Group": "家具",
    "Description": "ほとんどの2足歩行種族に対応するようデザインされた座り心地の良い椅子。お尻にあたる部分が少ししびれる。"
  },
  {
    "Id": "build156",
    "Name": "テーブル",
    "Group": "家具",
    "Description": "非磁性で耐食の素材で作られた多目的の作業用テーブル。"
  },
  {
    "Id": "build157",
    "Name": "ベッド",
    "Group": "家具",
    "Description": "ほとんどの2足歩行種族に対応するようデザインしてあり、四肢のはみだしが最低限に抑えられた広いシングルベッド。"
  },
  {
    "Id": "build158",
    "Name": "ライトテーブル",
    "Group": "デコレーション",
    "Description": "基地を美しくするための建築用の装飾品。"
  },
  {
    "Id": "build159",
    "Name": "棚パネル",
    "Group": "デコレーション",
    "Description": "基地を美しくするための建築用の装飾品。"
  },
  {
    "Id": "build161",
    "Name": "テルビウム・グロウ",
    "Group": "安定化したリアリティグリッチ",
    "Description": "稀に発生するグリッチで、機能障害を発生した惑星から回収できる。 居住可能基地で保管しても問題ないよう安定化されている。"
  },
  {
    "Id": "build162",
    "Name": "ライトフィッシャー",
    "Group": "安定化したリアリティグリッチ",
    "Description": "稀に発生するグリッチで、機能障害を発生した惑星から回収できる。 居住可能基地で保管しても問題ないよう安定化されている。"
  },
  {
    "Id": "build163",
    "Name": "バブルクラスター",
    "Group": "安定化したリアリティグリッチ",
    "Description": "稀に発生するグリッチで、機能障害を発生した惑星から回収できる。 居住可能基地で保管しても問題ないよう安定化されている。"
  },
  {
    "Id": "build164",
    "Name": "ヘクスプレートブッシュ",
    "Group": "安定化したリアリティグリッチ",
    "Description": "稀に発生するグリッチで、機能障害を発生した惑星から回収できる。 居住可能基地で保管しても問題ないよう安定化されている。"
  },
  {
    "Id": "build165",
    "Name": "グリッチ分離機",
    "Group": "安定化したリアリティグリッチ",
    "Description": "稀に発生するグリッチで、機能障害を発生した惑星から回収できる。 居住可能基地で保管しても問題ないよう安定化されている。"
  },
  {
    "Id": "build166",
    "Name": "骨化星",
    "Group": "安定化したリアリティグリッチ",
    "Description": "稀に発生するグリッチで、機能障害を発生した惑星から回収できる。 居住可能基地で保管しても問題ないよう安定化されている。"
  },
  {
    "Id": "build167",
    "Name": "ラトルスパイン",
    "Group": "安定化したリアリティグリッチ",
    "Description": "稀に発生するグリッチで、機能障害を発生した惑星から回収できる。 居住可能基地で保管しても問題ないよう安定化されている。"
  },
  {
    "Id": "build168",
    "Name": "ケーブルポッド",
    "Group": "安定化したリアリティグリッチ",
    "Description": "稀に発生するグリッチで、機能障害を発生した惑星から回収できる。 居住可能基地で保管しても問題ないよう安定化されている。"
  },
  {
    "Id": "build169",
    "Name": "カルキッシュルーム",
    "Group": "安定化したリアリティグリッチ",
    "Description": "稀に発生するグリッチで、機能障害を発生した惑星から回収できる。 居住可能基地で保管しても問題ないよう安定化されている。"
  },
  {
    "Id": "build170",
    "Name": "毛貝",
    "Group": "安定化したリアリティグリッチ",
    "Description": "稀に発生するグリッチで、機能障害を発生した惑星から回収できる。 居住可能基地で保管しても問題ないよう安定化されている。"
  },
  {
    "Id": "build171",
    "Name": "電気キューブ",
    "Group": "安定化したリアリティグリッチ",
    "Description": "稀に発生するグリッチで、機能障害を発生した惑星から回収できる。 居住可能基地で保管しても問題ないよう安定化されている。"
  },
  {
    "Id": "build172",
    "Name": "深海用の部屋",
    "Group": "水中建築モジュール",
    "Description": "基礎建築のコアモジュール。拡張可能の中心スペースができる。"
  },
  {
    "Id": "build173",
    "Name": "深海用の四角形部屋",
    "Group": "水中建築モジュール",
    "Description": "基礎建築のコアモジュールの四角い版。広い中心スペースは拡張可能。"
  },
  {
    "Id": "build174",
    "Name": "ムーンプールフロア",
    "Group": "水中建築モジュール",
    "Description": "ホログラムのムーンプールハッチ。 水中環境へのアクセスが簡単になる。\n\n自動加圧システムが外観を損なわない形で室内に設置されている。"
  },
  {
    "Id": "build175",
    "Name": "防水ドア",
    "Group": "水中建築モジュール",
    "Description": "全ての部屋や通路に使用できる圧縮密閉される標準的なドア。"
  },
  {
    "Id": "build176",
    "Name": "ガラストンネル",
    "Group": "水中建築モジュール",
    "Description": "深海の建設用の圧力をかけて強化したガラス製のトンネル。\n\n高度なナノミネラルのコーティングで深海でも視界を遮らず高いパフォーマンスを発揮することができる。"
  },
  {
    "Id": "build177",
    "Name": "L型ガラストンネル",
    "Group": "水中建築モジュール",
    "Description": "深海の建設用の圧力をかけて強化したガラス製のトンネル。\n\n高度なナノミネラルのコーティングで深海でも視界を遮らず高いパフォーマンスを発揮することができる。"
  },
  {
    "Id": "build178",
    "Name": "T型ガラストンネル",
    "Group": "水中建築モジュール",
    "Description": "深海の建設用の圧力をかけて強化したガラス製のトンネル。\n\n高度なナノミネラルのコーティングで深海でも視界を遮らず高いパフォーマンスを発揮することができる。"
  },
  {
    "Id": "build179",
    "Name": "X型ガラストンネル",
    "Group": "水中建築モジュール",
    "Description": "深海の建設用の圧力をかけて強化したガラス製のトンネル。\n\n高度なナノミネラルのコーティングで深海でも視界を遮らず高いパフォーマンスを発揮することができる。"
  },
  {
    "Id": "build180",
    "Name": "垂直型ガラストンネル",
    "Group": "水中建築モジュール",
    "Description": "深海の建設用の圧力をかけて強化したガラス製のトンネル。\n\n高度なナノミネラルのコーティングで深海でも視界を遮らず高いパフォーマンスを発揮することができる。"
  },
  {
    "Id": "build181",
    "Name": "ライトボックス",
    "Group": "ライトデバイス",
    "Description": "光を放つパネルのみで作られた\n特別な建築用モジュール。\n光の壁を建築するのに使用できる。\n\nボックスの色は配置の前または後に\n変更可能。使用には電力が必要となる。"
  },
  {
    "Id": "build182",
    "Name": "研究室用ランプ",
    "Group": "取り付け家具",
    "Description": "寿命が改良され、フルリサイクル可能な部品でできた低エネルギー消費の照明。"
  },
  {
    "Id": "build204",
    "Name": "基礎支柱4本セット",
    "Group": "建設アイテム",
    "Description": "高架建築に使う4本足のプレハブセット。"
  },
  {
    "Id": "build205",
    "Name": "基盤支柱",
    "Group": "建設アイテム",
    "Description": "高層建築物の脚部を支える強化済み非鉄金属。"
  },
  {
    "Id": "build206",
    "Name": "立方体部屋のルーフキャップ",
    "Group": "建築モジュール",
    "Description": "立方体状の構造物の屋根を装飾し強化する、立方体部屋用のルーフキャップ。"
  },
  {
    "Id": "build207",
    "Name": "ホログラムドア",
    "Group": "建築モジュール",
    "Description": "内部の温度や毒性レベルを維持しつつ、どの構造物へも素早く入れるようになる優雅なホログラムドア。"
  },
  {
    "Id": "build213",
    "Name": "白色ライト",
    "Group": "デコレーション",
    "Description": "基地を照らす色付きの照明。"
  },
  {
    "Id": "build214",
    "Name": "シーリングライト",
    "Group": "デコレーション",
    "Description": "基地を美しくするための建築用の装飾品。"
  },
  {
    "Id": "build215",
    "Name": "はしご",
    "Group": "建設アイテム",
    "Description": "壁に取り付けるため強化された固定金具のある強くて軽いはしご。"
  },
  {
    "Id": "build219",
    "Name": "ソファ",
    "Group": "デコレーション",
    "Description": "基地を美しくするための建築用の装飾品。"
  },
  {
    "Id": "build220",
    "Name": "コーナーソファ",
    "Group": "デコレーション",
    "Description": "基地を美しくするための建築用の装飾品。"
  },
  {
    "Id": "build221",
    "Name": "スウェプトソファ",
    "Group": "デコレーション",
    "Description": "基地を美しくするための建築用の装飾品。"
  },
  {
    "Id": "build222",
    "Name": "モニターステーション大",
    "Group": "デコレーション",
    "Description": "基地を美しくするための建築用の装飾品。"
  },
  {
    "Id": "build223",
    "Name": "シンプルなデスク",
    "Group": "デコレーション",
    "Description": "基地を美しくするための建築用の装飾品。"
  },
  {
    "Id": "build224",
    "Name": "カーブしたデスク",
    "Group": "デコレーション",
    "Description": "基地を美しくするための建築用の装飾品。"
  },
  {
    "Id": "build225",
    "Name": "モニターステーション",
    "Group": "デコレーション",
    "Description": "基地を美しくするための建築用の装飾品。"
  },
  {
    "Id": "build226",
    "Name": "カウンター",
    "Group": "デコレーション",
    "Description": "基地を美しくするための建築用の装飾品。"
  },
  {
    "Id": "build227",
    "Name": "壁用ユニット",
    "Group": "デコレーション",
    "Description": "壁掛け型の装飾用ストレージ。"
  },
  {
    "Id": "build228",
    "Name": "引き出し",
    "Group": "デコレーション",
    "Description": "基地を美しくするための建築用の装飾品。"
  },
  {
    "Id": "build229",
    "Name": "ストレージパネル",
    "Group": "デコレーション",
    "Description": "基地を美しくするための建築用の装飾品。"
  },
  {
    "Id": "build230",
    "Name": "八角形のキャビネット",
    "Group": "デコレーション",
    "Description": "基地を美しくするための建築用の装飾品。"
  },
  {
    "Id": "build231",
    "Name": "背の高いキャビネット",
    "Group": "デコレーション",
    "Description": "基地を美しくするための建築用の装飾品。"
  },
  {
    "Id": "build232",
    "Name": "ロッカー",
    "Group": "デコレーション",
    "Description": "基地を美しくするための建築用の装飾品。"
  },
  {
    "Id": "build233",
    "Name": "サイドパネル",
    "Group": "デコレーション",
    "Description": "基地を美しくするための建築用の装飾品。"
  },
  {
    "Id": "build234",
    "Name": "フロアマット",
    "Group": "デコレーション",
    "Description": "基地を美しくするための建築用の装飾品。"
  },
  {
    "Id": "build235",
    "Name": "フラッグ1",
    "Group": "デコレーション",
    "Description": "基地を美しくするための建築用の装飾品。"
  },
  {
    "Id": "build236",
    "Name": "フラッグ2",
    "Group": "デコレーション",
    "Description": "基地を美しくするための建築用の装飾品。"
  },
  {
    "Id": "build237",
    "Name": "フラッグ3",
    "Group": "デコレーション",
    "Description": "基地を美しくするための建築用の装飾品。"
  },
  {
    "Id": "build238",
    "Name": "フラッグ4",
    "Group": "デコレーション",
    "Description": "基地を美しくするための建築用の装飾品。"
  },
  {
    "Id": "build239",
    "Name": "ウォールフラッグ1",
    "Group": "デコレーション",
    "Description": "基地を美しくするための建築用の装飾品。"
  },
  {
    "Id": "build240",
    "Name": "ウォールフラッグ2",
    "Group": "デコレーション",
    "Description": "基地を美しくするための建築用の装飾品。"
  },
  {
    "Id": "build241",
    "Name": "ウォールフラッグ3",
    "Group": "デコレーション",
    "Description": "基地を美しくするための建築用の装飾品。"
  },
  {
    "Id": "build242",
    "Name": "技術パネル",
    "Group": "デコレーション",
    "Description": "装飾用途向けの機能の無い技術パネル。"
  },
  {
    "Id": "build243",
    "Name": "壁用ファン",
    "Group": "デコレーション",
    "Description": "壁に設置する装飾用の換気ファン。"
  },
  {
    "Id": "build244",
    "Name": "壁用スクリーン",
    "Group": "デコレーション",
    "Description": "壁掛け型の装飾用映像スクリーン。"
  },
  {
    "Id": "build245",
    "Name": "サーバー",
    "Group": "デコレーション",
    "Description": "基地を美しくするための建築用の装飾品。"
  },
  {
    "Id": "build246",
    "Name": "シーリングパネル",
    "Group": "デコレーション",
    "Description": "基地を美しくするための建築用の装飾品。"
  },
  {
    "Id": "build247",
    "Name": "キャニスター付きのラック",
    "Group": "デコレーション",
    "Description": "基地を美しくするための建築用の装飾品。"
  },
  {
    "Id": "build248",
    "Name": "ロボットの腕",
    "Group": "デコレーション",
    "Description": "基地を美しくするための建築用の装飾品。"
  },
  {
    "Id": "build249",
    "Name": "フラットパネル",
    "Group": "デコレーション",
    "Description": "基地を美しくするための建築用の装飾品。"
  },
  {
    "Id": "build250",
    "Name": "オシロスコープ",
    "Group": "デコレーション",
    "Description": "基地を美しくするための建築用の装飾品。"
  },
  {
    "Id": "build253",
    "Name": "大きなくさび",
    "Group": "デコレーション",
    "Description": "基本的な構造建築用アイテム。"
  },
  {
    "Id": "build254",
    "Name": "小さなくさび",
    "Group": "デコレーション",
    "Description": "基本的な構造建築用アイテム。"
  },
  {
    "Id": "build255",
    "Name": "ピラミッド",
    "Group": "デコレーション",
    "Description": "基本的な構造建築用アイテム。"
  },
  {
    "Id": "build256",
    "Name": "曲がったパイプ",
    "Group": "デコレーション",
    "Description": "基本的な構造建築用アイテム。"
  },
  {
    "Id": "build257",
    "Name": "パイプ",
    "Group": "デコレーション",
    "Description": "基本的な構造建築用アイテム。"
  },
  {
    "Id": "build258",
    "Name": "シリンダー",
    "Group": "デコレーション",
    "Description": "基本的な構造建築用アイテム。"
  },
  {
    "Id": "build259",
    "Name": "キューブ",
    "Group": "デコレーション",
    "Description": "基本的な構造建築用アイテム。"
  },
  {
    "Id": "build260",
    "Name": "球体",
    "Group": "デコレーション",
    "Description": "基本的な構造建築用アイテム。"
  },
  {
    "Id": "build261",
    "Name": "壁",
    "Group": "デコレーション",
    "Description": "強化された壁モジュール。銀河中に広く存在する基本的なアイテム。\n\n建築基準2.3bの普遍的な建造物を作成でき、他のプレハブ建築物との互換性も高い。素早くグリッドスナップすれば即座にシェルターのレイアウトを組み立てることができる。"
  },
  {
    "Id": "build266",
    "Name": "貨物船内用壁",
    "Group": "貨物船内装モジュール",
    "Description": "この拡張モジュールを使用すると、\n大型の宇宙船内部に居住空間を\n素早く建設できる。\n \n建設用ユニットはあらかじめ\n組み立ててあり、圧力隔壁と必要な\n接続用ポイントも付属している。"
  },
  {
    "Id": "build270",
    "Name": "ステッカー",
    "Group": "デコレーション",
    "Description": "配置自由な装飾用ステッカー。"
  },
  {
    "Id": "build272",
    "Name": "古い潜水球",
    "Group": "アンロック可能なヘルメット",
    "Description": "いわくつきのエクソスーツデザインオーバーライド。 一度身に着けると、永遠に深海からの囁きが聞こえてくるようになり使用者を苦しめることになる。\nエクソスーツのデザインは外見変更モジュールで変更できる。"
  },
  {
    "Id": "build273",
    "Name": "青銅の球体像",
    "Group": "アンロック可能なデコレーション",
    "Description": "建設可能な基地装飾品で、\n青銅の特製鋳造品。\n古代の原子生物を模した像。\n多くの初期の探検家はこの生物を\n追い求めて旅をしていた。"
  },
  {
    "Id": "build274",
    "Name": "銀の球体像",
    "Group": "アンロック可能なデコレーション",
    "Description": "建設可能な基地装飾品で、\n銀の特製鋳造品。\n古代の原子生物を模した像。\n多くの初期の探検家はこの生物を\n追い求めて旅をしていた。"
  },
  {
    "Id": "build275",
    "Name": "金の球体像",
    "Group": "アンロック可能なデコレーション",
    "Description": "建設可能な基地装飾品で、\n金の特製鋳造品。\n古代の原子生物を模した像。\n多くの初期の探検家はこの生物を\n追い求めて旅をしていた。"
  },
  {
    "Id": "build276",
    "Name": "青銅のディプロ像",
    "Group": "アンロック可能なデコレーション",
    "Description": "建設可能な基地装飾品で、\n青銅の特製鋳造品。\n首の長い四足歩行生物を模した像。"
  },
  {
    "Id": "build277",
    "Name": "銀のディプロ像",
    "Group": "アンロック可能なデコレーション",
    "Description": "建設可能な基地装飾品で、\n銀の特製鋳造品。\n首の長い四足歩行生物を模した像。"
  },
  {
    "Id": "build278",
    "Name": "金のディプロ像",
    "Group": "アンロック可能なデコレーション",
    "Description": "建設可能な基地装飾品で、\n金の特製鋳造品。\n首の長い四足歩行生物を模した像。"
  },
  {
    "Id": "build279",
    "Name": "青銅のゲック像",
    "Group": "アンロック可能なデコレーション",
    "Description": "建設可能な基地装飾品で、\n青銅の特製鋳造品。\n空に向かってジェスチャーする\nゲックを模した像。"
  },
  {
    "Id": "build280",
    "Name": "銀のゲック像",
    "Group": "アンロック可能なデコレーション",
    "Description": "建設可能な基地装飾品で、\n銀の特製鋳造品。\n空に向かってジェスチャーする\nゲックを模した像。"
  },
  {
    "Id": "build281",
    "Name": "金のゲック像",
    "Group": "アンロック可能なデコレーション",
    "Description": "建設可能な基地装飾品で、\n金の特製鋳造品。\n空に向かってジェスチャーする\nゲックを模した像。"
  },
  {
    "Id": "build282",
    "Name": "青銅のどまにし像",
    "Group": "アンロック可能なデコレーション",
    "Description": "建設可能な基地装飾品で、\n青銅の特製鋳造品。\nシンボルシップ、\n旧「どまにし」を模した像。"
  },
  {
    "Id": "build283",
    "Name": "銀のどまにし像",
    "Group": "アンロック可能なデコレーション",
    "Description": "建設可能な基地装飾品で、\n銀の特製鋳造品。\nシンボルシップ、\n旧「どまにし」を模した像。"
  },
  {
    "Id": "build284",
    "Name": "金のどまにし像",
    "Group": "アンロック可能なデコレーション",
    "Description": "建設可能な基地装飾品で、\n金の特製鋳造品。\nシンボルシップ、\n旧「どまにし」を模した像。"
  },
  {
    "Id": "build285",
    "Name": "青銅のセンチネルウォーカー像",
    "Group": "アンロック可能なデコレーション",
    "Description": "建設可能な基地装飾品で、\n青銅の特製鋳造品。\n上級戦闘ユニット、\nセンチネルウォーカーを模した像。"
  },
  {
    "Id": "build286",
    "Name": "銀のセンチネルウォーカー像",
    "Group": "アンロック可能なデコレーション",
    "Description": "建設可能な基地装飾品で、\n銀の特製鋳造品。\n上級戦闘ユニット、\nセンチネルウォーカーを模した像。"
  },
  {
    "Id": "build287",
    "Name": "金のセンチネルウォーカー像",
    "Group": "アンロック可能なデコレーション",
    "Description": "建設可能な基地装飾品で、\n金の特製鋳造品。\n上級戦闘ユニット、\nセンチネルウォーカーを模した像。"
  },
  {
    "Id": "build288",
    "Name": "青銅のアトラス像",
    "Group": "アンロック可能なデコレーション",
    "Description": "建設可能な基地装飾品で、\n青銅の特製鋳造品。\nアトラスインターフェースの\nデコレートレプリカで、\n未知の動力で、コア部分が回転する。"
  },
  {
    "Id": "build289",
    "Name": "銀のアトラス像",
    "Group": "アンロック可能なデコレーション",
    "Description": "建設可能な基地装飾品で、\n銀の特製鋳造品。\nアトラスインターフェースの\nデコレートレプリカで、\n未知の動力で、コア部分が回転する。"
  },
  {
    "Id": "build290",
    "Name": "金のアトラス像",
    "Group": "アンロック可能なデコレーション",
    "Description": "建設可能な基地装飾品で、\n金の特製鋳造品。\nアトラスインターフェースの\nデコレートレプリカで、\n未知の動力で、コア部分が回転する。"
  },
  {
    "Id": "build291",
    "Name": "青銅の宇宙飛行士像",
    "Group": "アンロック可能なデコレーション",
    "Description": "建設可能な基地装飾品で、\n青銅の特製鋳造品。\n全ての惑星探検家への\n記念品として贈られた\n宇宙飛行士の像。"
  },
  {
    "Id": "build292",
    "Name": "銀の宇宙飛行士像",
    "Group": "アンロック可能なデコレーション",
    "Description": "建設可能な基地装飾品で、\n銀の特製鋳造品。\n全ての惑星探検家への\n記念品として贈られた\n宇宙飛行士の像。"
  },
  {
    "Id": "build293",
    "Name": "金の宇宙飛行士像",
    "Group": "アンロック可能なデコレーション",
    "Description": "建設可能な基地装飾品で、\n金の特製鋳造品。\n全ての惑星探検家への\n記念品として贈られた\n宇宙飛行士の像。"
  },
  {
    "Id": "build294",
    "Name": "銀河ハブステッカー",
    "Group": "デコレーション",
    "Description": "設置可能な特製ステッカー。\nこれで基地に遊び心を加えよう。\nこのステッカーは「一緒に冒険しよう」と\nメッセージが書いてあるエンブレムを\n模している。"
  },
  {
    "Id": "build295",
    "Name": "賛成ステッカー",
    "Group": "デコレーション",
    "Description": "設置可能な特製ステッカー。\nこれで基地に遊び心を加えよう。\nこのステッカーは賛成を表す\nジェスチャーを模している。"
  },
  {
    "Id": "build296",
    "Name": "ナーダステッカー",
    "Group": "デコレーション",
    "Description": "設置可能な特製ステッカー。\nこれで基地に遊び心を加えよう。\nこのステッカーはコーバックスの\n祭司ナーダを模している。"
  },
  {
    "Id": "build297",
    "Name": "ポーロステッカー",
    "Group": "デコレーション",
    "Description": "設置可能な特製ステッカー。\nこれで基地に遊び心を加えよう。\nこのステッカーはゲックの\n専門家 ポーロを模している。"
  },
  {
    "Id": "build298",
    "Name": "アポロステッカー",
    "Group": "デコレーション",
    "Description": "設置可能な特製ステッカー。\nこれで基地に遊び心を加えよう。\nこのステッカーはトラベラー\nアポロを模している。"
  },
  {
    "Id": "build299",
    "Name": "アルテミスステッカー",
    "Group": "デコレーション",
    "Description": "設置可能な特製ステッカー。\nこれで基地に遊び心を加えよう。\nこのステッカーはトラベラー\nアルテミスを模している。"
  },
  {
    "Id": "build300",
    "Name": "ナルステッカー",
    "Group": "デコレーション",
    "Description": "設置可能な特製ステッカー。\nこれで基地に遊び心を加えよう。\nこのステッカーはトラベラー \nナルを模している。"
  },
  {
    "Id": "build301",
    "Name": "ロボティックコンパニオン",
    "Group": "個人用ドローン",
    "Description": "完璧なプログラムが施された\nエラーの発生しないドローン。\n\nこの小さなロボットはあなたの基地で\n活気ある存在となり、常に小さな\nハミングが聞こえてくるような喜びと\n笑いの絶えない生活をもたらしてくれる。"
  },
  {
    "Id": "build302",
    "Name": "拡大キューブガジェット",
    "Group": "アンロック可能なデコレーション",
    "Description": "特別な鑑賞物。\n\n精密に作られたガジェットで局部的な\n重力フィールドを使用している。 \n基地を訪れる客をもてなすアイテム。"
  },
  {
    "Id": "build303",
    "Name": "球体ホログラムガジェット",
    "Group": "アンロック可能なデコレーション",
    "Description": "基地用の特別な鑑賞物。\n\nこのガジェットは銀河の中に存在する\n数百京の内の一つの天体のホログラムを\n映し出している。"
  },
  {
    "Id": "build304",
    "Name": "果樹",
    "Group": "有機物デコレーション",
    "Description": "大型の観葉果樹。\n\n果実型をしており、\n毒性や形態は栽培する地域の気候や\n送粉者の状態によって異なる。"
  },
  {
    "Id": "build305",
    "Name": "低木",
    "Group": "有機物デコレーション",
    "Description": "薄く、果実の生らない木。 \n根系は菌性の共生生物が\n存在していることが多い。\n\nキノコ類が育ちやすい環境を\n提供しており、菌に毒性はなく\n他の個体に繁殖することはない。"
  },
  {
    "Id": "build306",
    "Name": "常緑樹",
    "Group": "有機物デコレーション",
    "Description": "頑丈な常緑樹で、\n様々な気候で自生することができる。\n\n裏面が銀色のろう質の葉は\n効果の高い集光能力を有しており、\n一年を通して色彩と光を楽しむことが\nできる。"
  },
  {
    "Id": "build307",
    "Name": "肉食低木",
    "Group": "有機物デコレーション",
    "Description": "中型の観葉植物。 \n一枚一枚の葉が粘着性の薄い乳液に\n覆われており、葉に乗った虫は\n乳液の中に含まれている消化ホルモンに\nゆっくりと吸収されていく。\n\n素手での接触は避けることを推奨する。"
  },
  {
    "Id": "build308",
    "Name": "ドワーフヤシ",
    "Group": "有機物デコレーション",
    "Description": "大きなヤシ類の木を管理しやすい\nサイズにした木。\n\n屋外に設置すると\n野生動物を呼び寄せたり、\n空気を清浄することができる。"
  },
  {
    "Id": "build309",
    "Name": "謎のコーン",
    "Group": "有機物デコレーション",
    "Description": "発芽中の観葉用コーン。 \n様々な色合いのものが存在する。 \n鑑賞用の野生動物を\n呼び寄せることもある。\n\n自然発生することはないため、\n人工的に授粉させる必要がある。"
  },
  {
    "Id": "build310",
    "Name": "小さな水槽",
    "Group": "水中生物観察モジュール",
    "Description": "水中動物の行動を観察できる小さなインテリア。\n\n再生型エネルギー、ポンプアレイ、自動洗浄フィルターシステムを装備しているためメンテナンスは全く必要ない。"
  },
  {
    "Id": "build311",
    "Name": "巻きサンゴ",
    "Group": "有機物デコレーション",
    "Description": "殻の形に合わせて成長した繊細な海の\n無脊椎動物。ループの形が目を引く\n風変りだが愛らしいフォルムが特徴的。"
  },
  {
    "Id": "build312",
    "Name": "海のクリスタル",
    "Group": "有機物デコレーション",
    "Description": "目を見張る結晶状の海の鉱物の大群。 \nこの結晶はシャードのような形状で\n形成され、少し変わった\nマーブルカラーが特徴となっている。"
  },
  {
    "Id": "build313",
    "Name": "枝付き燭台",
    "Group": "有機物デコレーション",
    "Description": "ぼんやりと光るオーブ型の花が特徴的な\n目を引く植物。あらゆる水源から酸素を\n吸収し摂取することができる。\n陸にも水中でも生息可能。"
  },
  {
    "Id": "build314",
    "Name": "フジツボ",
    "Group": "有機物デコレーション",
    "Description": "海でよくみられる節足動物。\n水中の動かないオブジェクトや\nゆっくりと動いているオブジェクトを\n覆っていることが多い。\n\n好きな場所に貼れば、基地を\n海の家のような雰囲気に変えらえる。"
  },
  {
    "Id": "build315",
    "Name": "花火",
    "Group": "使用可能な花火装置",
    "Description": "マグネシウムとエメリルが豊富な豪華絢爛な花火。 着火すると空に美しい煌めきを作り上げる。\n\nビルドメニュー(BUILD_MENU)から打ち上げチューブを設置できる。 警告:生物に向けて発砲しないこと。 室内での使用は推奨しない。"
  },
  {
    "Id": "build316",
    "Name": "携帯現実ジェネレーター",
    "Group": "アンロック可能なデコレーション",
    "Description": "基地用の特別な鑑賞物。\n\n現実では不可能な位置から観察した\n現実そのもののモデル。驚嘆に値する\nその詳細な再現性は、強力なレンズを\n使用して観察しても全てを見切ることは\n出来ない程だ。"
  },
  {
    "Id": "build317",
    "Name": "テラリウム",
    "Group": "生物飼育用特殊設備",
    "Description": "動物の生態を研究するための\n小型観察ユニット。\n\n栄養リサイクル、空気浄化、排泄物処理の\n機能を持ち、完全自給自足の生態系を\n作り出すことができる。"
  },
  {
    "Id": "build318",
    "Name": "ホカケヤシ",
    "Group": "有機物デコレーション",
    "Description": "大きな葉を持ち、暑さに強い木。\n\n広い葉は鉱物質を含み、自生地の強烈な\n陽射しを遮る覆いとなっている。"
  },
  {
    "Id": "build319",
    "Name": "グローブツリー",
    "Group": "有機物デコレーション",
    "Description": "細い幹に大きな多肉質の根という、\n高温気候によく適応した体構造を\n持つ樹状植物。\n\n球根は絞り汁が飲料になるが、\nよほどの非常時でなければ\nおすすめはできない。"
  },
  {
    "Id": "build320",
    "Name": "石庭",
    "Group": "有機物デコレーション",
    "Description": "庭園モジュール。装飾用の岩石が\n付属する。内蔵の極細繊維製マット\nにより、湿度が最適な状態に調整される。"
  },
  {
    "Id": "build321",
    "Name": "小さな木製の天井",
    "Group": "木製の建造部品",
    "Description": "木製のドアフレームに挿入する小さなドア。"
  },
  {
    "Id": "build322",
    "Name": "木製電動ドア",
    "Group": "木製の建造部品",
    "Description": "電動ドア。電力グリッドに接続し、各種スイッチで操作する。\n\n扉は圧縮した木片を樹脂で固めた\n成形木材製。"
  },
  {
    "Id": "build324",
    "Name": "木製屋根入隅",
    "Group": "木製の建造部品",
    "Description": "屋根の構成部品。\n角張った屋根を作るのに必要。\n\n圧縮した木片を樹脂で固めた成形木材製。"
  },
  {
    "Id": "build325",
    "Name": "小さな金属製のドア",
    "Group": "金属製の建造部品",
    "Description": "金属製のドアフレームに挿入する小さなドア。"
  },
  {
    "Id": "build326",
    "Name": "金属電動ドア",
    "Group": "金属製の建造部品",
    "Description": "電動ドア。電力グリッド\nに接続し、各種スイッチで操作する。\n\n扉は高強度合金製。"
  },
  {
    "Id": "build328",
    "Name": "金属屋根入隅",
    "Group": "金属製の建造部品",
    "Description": "屋根の構成部品。\n角張った屋根を作るのに必要。\n\n高強度合金製。"
  },
  {
    "Id": "build329",
    "Name": "小さなコンクリート製のドア",
    "Group": "コンクリート製の建造部品",
    "Description": "コンクリート製のドアフレームに挿入する小さなドア。"
  },
  {
    "Id": "build330",
    "Name": "コンクリート電動ドア",
    "Group": "コンクリート製の建造部品",
    "Description": "電動ドア。電力グリッドに接続し、各種スイッチで操作する。\n\n扉は強化コンクリート製。"
  },
  {
    "Id": "build332",
    "Name": "コンクリート屋根入隅",
    "Group": "コンクリート製の建造部品",
    "Description": "屋根の構成部品。\n角張った屋根を作るのに必要。\n\n強化コンクリート製。"
  },
  {
    "Id": "build336",
    "Name": "照明",
    "Group": "取り付け家具",
    "Description": "寿命が改良され、フルリサイクル可能な部品でできた低エネルギー消費の照明。"
  },
  {
    "Id": "build337",
    "Name": "アノマリーステッカー",
    "Group": "デコレーション",
    "Description": "設置可能な特製ステッカー。\nこれで基地に遊び心を加えよう。\nこのステッカーはトラベラーアノマリーを\n模している。"
  },
  {
    "Id": "build338",
    "Name": "木製トライアングル",
    "Group": "木製の建造部品",
    "Description": "木造建築物の床を作る基本部品。 シンプルな形状だけに、非常に多様な構造に組みあげることができる。"
  },
  {
    "Id": "build339",
    "Name": "小型木製トライアングル",
    "Group": "木製の建造部品",
    "Description": "木造建築物の床を作る基本部品。 シンプルな形状だけに、非常に多様な構造に組みあげることができる。"
  },
  {
    "Id": "build340",
    "Name": "金属製トライアングル",
    "Group": "金属製の建造部品",
    "Description": "金属製建築物の床を作る基本部品。 シンプルな形状だけに、非常に多様な構造に組みあげることができる。"
  },
  {
    "Id": "build341",
    "Name": "小型金属製トライアングル",
    "Group": "金属製の建造部品",
    "Description": "金属製建築物の床を作る基本部品。 シンプルな形状だけに、非常に多様な構造に組みあげることができる。"
  },
  {
    "Id": "build342",
    "Name": "コンクリート製トライアングル",
    "Group": "コンクリート製の建造部品",
    "Description": "コンクリート建築物の床を作る基本部品。 シンプルな形状だけに、非常に多様な構造に組みあげることができる。"
  },
  {
    "Id": "build343",
    "Name": "小型コンクリート製トライアングル",
    "Group": "コンクリート製の建造部品",
    "Description": "コンクリート建築物の床を作る基本部品。 シンプルな形状だけに、非常に多様な構造に組みあげることができる。"
  },
  {
    "Id": "build344",
    "Name": "青色ライト",
    "Group": "デコレーション",
    "Description": "基地を照らす色付きの照明。"
  },
  {
    "Id": "build345",
    "Name": "桃色ライト",
    "Group": "デコレーション",
    "Description": "基地を照らす色付きの照明。"
  },
  {
    "Id": "build346",
    "Name": "黄色ライト",
    "Group": "デコレーション",
    "Description": "基地を照らす色付きの照明。"
  },
  {
    "Id": "build347",
    "Name": "緑色ライト",
    "Group": "デコレーション",
    "Description": "基地を照らす色付きの照明。"
  },
  {
    "Id": "build348",
    "Name": "赤色ライト",
    "Group": "デコレーション",
    "Description": "基地を照らす色付きの照明。"
  },
  {
    "Id": "build359",
    "Name": "ライトフロア",
    "Group": "ライトデバイス",
    "Description": "光を発するパネルで作られた\n特別な建築モジュール。\n発光床の作成に使用できる。\n\n設置前後に色を塗り直すことができる。\n使用するには電力が必要だ。"
  },
  {
    "Id": "build360",
    "Name": "バイトビートデバイス",
    "Group": "オーディオシンセサイザー",
    "Description": "先進的なオーディオ生成プログラムで\n使用者が複雑な音楽アレンジを合成\nできるようにする。\n\n複数のデバイスを並べたり\nライトにつなげたりすれば\n見応えのある表示を生成できる。"
  },
  {
    "Id": "build361",
    "Name": "バイトビートケーブル",
    "Group": "バイトビートエクステンション",
    "Description": "高等なケーブルでひとつかそれ以上の バイトビートジェネレーターとリンクしたり、 バイトビートスイッチ をネットワークにつないだりできる。\n\n信号はつながれたライトやデバイスと同期して波形を生み出す。"
  },
  {
    "Id": "build362",
    "Name": "バイトビートスイッチ",
    "Group": "バイトビートエクステンション",
    "Description": "音楽用のスイッチングデバイスで、\nバイトビートジェネレーターが生み出した\n波形の信号を電子信号へと変換して\nライトや他のデバイスとつなぐ。"
  },
  {
    "Id": "build363",
    "Name": "エクソスーツバックパック",
    "Group": "エクソスーツ外装カスタマイズ",
    "Description": "特製エクソスーツデザインオーバーライド。\n\n頑丈なモジュール式バックパックユニット。\n宇宙探索の旧時代を思わせるデザインをしている。\n\nエクソスーツのデザインは外見変更モジュールで変更できる。"
  },
  {
    "Id": "build364",
    "Name": "レインボー排気煙",
    "Group": "ジェットパック排気オーバーライド",
    "Description": "特製エクソスーツデザインオーバーライド。\n\n精確に調整された多色燃料噴射装置がジェットパックの排出成分を変化させ、色とりどりの排気煙を吐き出す。\n\nエクソスーツのデザインは外見変更モジュールで変更できる。"
  },
  {
    "Id": "build365",
    "Name": "反物質排気煙",
    "Group": "ジェットパック排気オーバーライド",
    "Description": "特製エクソスーツデザインオーバーライド。\n\n重粒子抑制装置がジェットパックの排出成分を変化させ、特徴的な黒色の排気煙を吐き出す。\n\nエクソスーツのデザインは外見変更モジュールで変更できる。"
  },
  {
    "Id": "build366",
    "Name": "赤色排気煙",
    "Group": "ジェットパック排気オーバーライド",
    "Description": "特製エクソスーツデザインオーバーライド。\n\nカドミウム注入ノズルが\n力強い赤色をジェットパックの排気煙に加える。\n\nエクソスーツのデザインは外見変更モジュールで変更できる。"
  },
  {
    "Id": "build367",
    "Name": "緑色排気煙",
    "Group": "ジェットパック排気オーバーライド",
    "Description": "特製エクソスーツデザインオーバーライド。\n\nエメリル注入ノズルが豊かな緑色をジェットパックの排気煙に加える。\n\nエクソスーツのデザインは外見変更モジュールで変更できる。"
  },
  {
    "Id": "build368",
    "Name": "青色排気煙",
    "Group": "ジェットパック排気オーバーライド",
    "Description": "特製エクソスーツデザインオーバーライド。\n\nインジウム注入ノズルが目の覚めるような青色をジェットパックの排気煙に加える。\n\nエクソスーツのデザインは外見変更モジュールで変更できる。"
  },
  {
    "Id": "build369",
    "Name": "カラフル宇宙船排気煙",
    "Group": "宇宙船外装オーバーライド",
    "Description": "特製の 宇宙船排気モジュール。\n\n精確に調整された多色燃料噴射装置が\nパルスドライブの排出成分を変化させ、\n色とりどりの排気煙を吐き出す。\n\nこの テクノロジー を\n宇宙船のアイテムケースにインストールすれば、\nエンジンからの排気煙の外見を変えられる。"
  },
  {
    "Id": "build370",
    "Name": "ステルス宇宙船排気煙",
    "Group": "宇宙船外装オーバーライド",
    "Description": "特製の 宇宙船排気モジュール。\n\n重粒子抑制装置がパルスドライブの排出成分を変化させ、\n特徴的な黒色の排気煙を吐き出す。\n\nこの テクノロジー を\n宇宙船のアイテムケースにインストールすれば、\nエンジンからの排気煙の外見を変えられる。"
  },
  {
    "Id": "build371",
    "Name": "カドミウム宇宙船排気煙",
    "Group": "宇宙船外装オーバーライド",
    "Description": "特製の 宇宙船排気モジュール。\n\nカドミウム注入ノズルが\n力強い赤色をパルスドライブの排気煙に加える。\n\nこの テクノロジー を\n宇宙船のアイテムケースにインストールすれば、\nエンジンからの排気煙の外見を変えられる。"
  },
  {
    "Id": "build372",
    "Name": "エメリル宇宙船排気煙",
    "Group": "宇宙船外装オーバーライド",
    "Description": "特製の 宇宙船排気モジュール。\n\nエメリル注入ノズルが\n豊かな緑色をパルスドライブの排気煙に加える。\n\nこの テクノロジー を\n宇宙船のアイテムケースにインストールすれば、\nエンジンからの排気煙の外見を変えられる。"
  },
  {
    "Id": "build373",
    "Name": "金色の宇宙船排気煙",
    "Group": "宇宙船外装オーバーライド",
    "Description": "特製の 宇宙船排気モジュール。\n\n金注入ノズルが\n目もくらむような金色をパルスドライブの排気煙に加える。\n\nこの テクノロジー を\n宇宙船のアイテムケースにインストールすれば、\nエンジンからの排気煙の外見を変えられる。"
  },
  {
    "Id": "build374",
    "Name": "ねじれた茂み",
    "Group": "有機物デコレーション",
    "Description": "放射線にさらされた世界に生息する不思議な多肉植物で、\n無風状態でもかすかに揺れているように見える......。\n\n基地の景観を改良するために使用できる。"
  },
  {
    "Id": "build375",
    "Name": "傘状の木",
    "Group": "有機物デコレーション",
    "Description": "高濃度の放射線に適応するため進化した特徴的な形状の樹木。\n中心部にある核は輝いて野生生物をひきつけるが\n感覚器ではなく、あなたを見ているわけでもない。\n\n基地の景観を改良するために使用できる。"
  },
  {
    "Id": "build376",
    "Name": "絡みあった木",
    "Group": "有機物デコレーション",
    "Description": "濃厚なガンマ線による熱の中でも生存する美しい大型樹木で、\n樹幹には高エネルギー物質が埋め込まれている。\n\n基地の景観を改良するために使用できる。"
  },
  {
    "Id": "build377",
    "Name": "灼熱のキノコ",
    "Group": "有機物デコレーション",
    "Description": "この膨張した突起物は、\n地下に広がる網状の微細な胞子から急速に成長し、\n周囲の土壌を改善する。\n\n基地の景観を改良するために使用できる。"
  },
  {
    "Id": "build378",
    "Name": "番人の木",
    "Group": "有機物デコレーション",
    "Description": "この植物は作物として栽培されているものの、\n摂取は控えるのが望ましい。\n\n基地の景観を改良するために使用できる。"
  },
  {
    "Id": "build379",
    "Name": "触手キノコ",
    "Group": "有機物デコレーション",
    "Description": "この素晴らしい建築用花卉（かき）は、\n非常に人気の高い二種類の美を兼ね備えている。\nビクビクと動く触手と巨大な菌類だ。\n\n基地の景観を改良するために使用できる。"
  },
  {
    "Id": "build380",
    "Name": "魅惑のサボテン",
    "Group": "有機物デコレーション",
    "Description": "優美で柔らかい花糸（かし）が\nこの砂漠植物の表面を這っており、\n水分吸収のために表面積を増やしている。\nまた、非常に魅力的な外見である。\n\n基地の景観を改良するために使用できる。"
  },
  {
    "Id": "build381",
    "Name": "祝賀用サボテン",
    "Group": "有機物デコレーション",
    "Description": "見事な多肉多汁の球形植物で、\n非常に愛らしい姿をしており、\n球根の頂点部分に雪のような美しい花弁を備える。\n\n基地の景観を改良するために使用できる。"
  },
  {
    "Id": "build382",
    "Name": "肉厚の木",
    "Group": "有機物デコレーション",
    "Description": "樹皮のせいで誤解されることが多いが、\n中身は荒くも硬くもなく、\n触ると柔らかで湿っている。\n表面上のしわで水を貯え、乾燥に備える。\n\n基地の景観を改良するために使用できる。"
  },
  {
    "Id": "build383",
    "Name": "冬越えの木",
    "Group": "有機物デコレーション",
    "Description": "丈夫な針葉樹で、耐寒性をもたらす酵素を含む\n樹液をめぐらせているため\n想像を絶するような低温環境でも生存できる。\n\n基地の景観を改良するために使用できる。"
  },
  {
    "Id": "build384",
    "Name": "凍てついたプランター",
    "Group": "有機物デコレーション",
    "Description": "雪が詰まった石製の桶状容器。\n氷雪世界で育つ\n小型の丈夫な植物を入れるのに最適。\n\n基地の景観を改良するために使用できる。"
  },
  {
    "Id": "build385",
    "Name": "太古の針葉樹",
    "Group": "有機物デコレーション",
    "Description": "この樹木の寿命は地質学的年代にまで達する。\n本来の生育地は熱量や光量が少なかったため、\n季節ごとに数ミリずつ生長する。\n標本だけでも植物学史上類を見ない大きさである。\n\n基地の景観を改良するために使用できる。"
  },
  {
    "Id": "build386",
    "Name": "海生岩",
    "Group": "有機物デコレーション",
    "Description": "海の塩分が結晶化した、不思議な無機形成物。\n水生生物やその化石を含むこともある。\n\n基地の景観を改良するために使用できる。"
  },
  {
    "Id": "build387",
    "Name": "鉱物のアーチ",
    "Group": "有機物デコレーション",
    "Description": "自然が生んだ驚くべき形状の地形。\n安定して加重に耐えるアーチ状鉱物で、\n内部は不思議な角度の晶洞石で満たされている。\n\n基地の景観を改良するために使用できる。"
  },
  {
    "Id": "build388",
    "Name": "宝石殻岩",
    "Group": "有機物デコレーション",
    "Description": "かつては廃棄されていた\n深層水晶採鉱の副産物だが、\n現在ではその美的価値が\nしっかりと認識されるようになっている。\n\n基地の景観を改良するために使用できる。"
  },
  {
    "Id": "build389",
    "Name": "奇妙な動物のバナー",
    "Group": "オーダーメイド個人識別バナー（旗）",
    "Description": "奇妙で変わった動物への興味を前面に押し出した特製 自己表現用アイテム。\n\n外見変更モジュール で自分のプロフィールにこのバナーを採用できる。"
  },
  {
    "Id": "build390",
    "Name": "ブクブクのバナー",
    "Group": "オーダーメイド個人識別バナー（旗）",
    "Description": "ブクブクした優しい生物と彼らが生み出す美味しい蜜への愛をこの見せびらかす特製 自己表現用アイテム。\n\n外見変更モジュール で自分のプロフィールにこのバナーを採用できる。"
  },
  {
    "Id": "build391",
    "Name": "専門家ポーロのバナー",
    "Group": "オーダーメイド個人識別バナー（旗）",
    "Description": "専門家ポーロはあなたがこの特製 自己表現用アイテム を喜んでくれることを望んでいる。あなたの旅に喜びをもたらしますように！\n\n外見変更モジュール で自分のプロフィールにこのバナーを採用できる。"
  },
  {
    "Id": "build392",
    "Name": "祭司ナーダのバナー",
    "Group": "オーダーメイド個人識別バナー（旗）",
    "Description": "身につけることで祭司ナーダがあなたのコンバージェンスに参加してくれるのはこの特製 自己表現用アイテム だけ！\n\n外見変更モジュール で自分のプロフィールにこのバナーを採用できる。"
  },
  {
    "Id": "build393",
    "Name": "銀河中心部バナー",
    "Group": "オーダーメイド個人識別バナー（旗）",
    "Description": "一緒に旅に出るときに身につけたい特製 自己表現用アイテム ！\n\n外見変更モジュール で自分のプロフィールにこのバナーを採用できる。"
  },
  {
    "Id": "build394",
    "Name": "きめ細かく美味なバナー",
    "Group": "オーダーメイド個人識別バナー（旗）",
    "Description": "美味を追求する銀河全料理法への傾倒を堂々と主張できる特製 自己表現用アイテム。\n\n外見変更モジュール で自分のプロフィールにこのバナーを採用できる。"
  },
  {
    "Id": "build395",
    "Name": "軌道エクソクラフト具現化装置",
    "Group": "エクソクラフト即時展開",
    "Description": "建設すると、自分の貨物船が同じ星系内にあれば、所有するエクソクラフトをどれでも召喚可能になる。\n\nエクソスーツクイックコマンドメニューで\n簡単に使用できる。"
  },
  {
    "Id": "build396",
    "Name": "電子クローキングユニット",
    "Group": "配電モジュール",
    "Description": "居住可能な基地を無線にして見た目を\n美しくするデバイス。\n\n電子クローキングユニットを\n電力が供給されている基地に建設すると、\nその場にあるすべての送電線が\n目立ちにくくなる。\n電力が十分な場合、ワイヤーは非表示でも\n電力供給は継続される。"
  }
]